{
    "imgHeight": 512,
    "imgWidth": 512,
    "objects": [
        {
            "label": "farmland",
            "polygon": [
                [
                    512,
                    438
                ],
                [
                    475,
                    440
                ],
                [
                    483,
                    512
                ],
                [
                    512,
                    512
                ]
            ]
        },
        {
            "label": "farmland",
            "polygon": [
                [
                    416,
                    512
                ],
                [
                    479,
                    512
                ],
                [
                    478,
                    506
                ],
                [
                    416,
                    511
                ]
            ]
        },
        {
            "label": "farmland",
            "polygon": [
                [
                    236,
                    512
                ],
                [
                    409,
                    512
                ],
                [
                    391,
                    408
                ],
                [
                    381,
                    408
                ],
                [
                    229,
                    413
                ]
            ]
        },
        {
            "label": "farmland",
            "polygon": [
                [
                    426,
                    274
                ],
                [
                    374,
                    263
                ],
                [
                    411,
                    441
                ],
                [
                    443,
                    437
                ]
            ]
        },
        {
            "label": "farmland",
            "polygon": [
                [
                    512,
                    434
                ],
                [
                    512,
                    345
                ],
                [
                    503,
                    288
                ],
                [
                    431,
                    274
                ],
                [
                    450,
                    439
                ]
            ]
        },
        {
            "label": "farmland",
            "polygon": [
                [
                    512,
                    291
                ],
                [
                    508,
                    290
                ],
                [
                    512,
                    320
                ]
            ]
        },
        {
            "label": "farmland",
            "polygon": [
                [
                    288,
                    407
                ],
                [
                    271,
                    254
                ],
                [
                    249,
                    255
                ],
                [
                    240,
                    236
                ],
                [
                    211,
                    233
                ],
                [
                    229,
                    409
                ]
            ]
        },
        {
            "label": "farmland",
            "polygon": [
                [
                    382,
                    404
                ],
                [
                    382,
                    395
                ],
                [
                    389,
                    395
                ],
                [
                    366,
                    273
                ],
                [
                    357,
                    272
                ],
                [
                    359,
                    261
                ],
                [
                    308,
                    250
                ],
                [
                    307,
                    262
                ],
                [
                    289,
                    262
                ],
                [
                    274,
                    260
                ],
                [
                    293,
                    406
                ]
            ]
        },
        {
            "label": "farmland",
            "polygon": [
                [
                    199,
                    512
                ],
                [
                    230,
                    512
                ],
                [
                    227,
                    477
                ],
                [
                    197,
                    479
                ]
            ]
        },
        {
            "label": "farmland",
            "polygon": [
                [
                    162,
                    512
                ],
                [
                    196,
                    512
                ],
                [
                    194,
                    480
                ],
                [
                    161,
                    482
                ]
            ]
        },
        {
            "label": "farmland",
            "polygon": [
                [
                    124,
                    512
                ],
                [
                    153,
                    512
                ],
                [
                    151,
                    480
                ],
                [
                    124,
                    481
                ]
            ]
        },
        {
            "label": "farmland",
            "polygon": [
                [
                    96,
                    512
                ],
                [
                    120,
                    512
                ],
                [
                    120,
                    483
                ],
                [
                    97,
                    485
                ],
                [
                    97,
                    484
                ]
            ]
        },
        {
            "label": "farmland",
            "polygon": [
                [
                    78,
                    512
                ],
                [
                    92,
                    512
                ],
                [
                    92,
                    484
                ],
                [
                    79,
                    484
                ]
            ]
        },
        {
            "label": "farmland",
            "polygon": [
                [
                    60,
                    512
                ],
                [
                    74,
                    512
                ],
                [
                    75,
                    486
                ],
                [
                    61,
                    486
                ]
            ]
        },
        {
            "label": "farmland",
            "polygon": [
                [
                    42,
                    512
                ],
                [
                    56,
                    512
                ],
                [
                    58,
                    487
                ],
                [
                    44,
                    486
                ]
            ]
        },
        {
            "label": "farmland",
            "polygon": [
                [
                    0,
                    504
                ],
                [
                    0,
                    512
                ],
                [
                    20,
                    512
                ],
                [
                    20,
                    503
                ]
            ]
        },
        {
            "label": "farmland",
            "polygon": [
                [
                    216,
                    346
                ],
                [
                    170,
                    346
                ],
                [
                    176,
                    474
                ],
                [
                    225,
                    469
                ]
            ]
        },
        {
            "label": "farmland",
            "polygon": [
                [
                    173,
                    473
                ],
                [
                    166,
                    346
                ],
                [
                    117,
                    346
                ],
                [
                    124,
                    476
                ]
            ]
        },
        {
            "label": "farmland",
            "polygon": [
                [
                    118,
                    473
                ],
                [
                    113,
                    347
                ],
                [
                    80,
                    348
                ],
                [
                    80,
                    477
                ]
            ]
        },
        {
            "label": "farmland",
            "polygon": [
                [
                    76,
                    477
                ],
                [
                    76,
                    407
                ],
                [
                    61,
                    406
                ],
                [
                    61,
                    346
                ],
                [
                    22,
                    346
                ],
                [
                    19,
                    414
                ],
                [
                    37,
                    413
                ],
                [
                    39,
                    417
                ],
                [
                    43,
                    417
                ],
                [
                    46,
                    479
                ]
            ]
        },
        {
            "label": "farmland",
            "polygon": [
                [
                    17,
                    347
                ],
                [
                    7,
                    347
                ],
                [
                    1,
                    461
                ],
                [
                    12,
                    461
                ]
            ]
        },
        {
            "label": "farmland",
            "polygon": [
                [
                    0,
                    417
                ],
                [
                    0,
                    436
                ],
                [
                    2,
                    417
                ]
            ]
        },
        {
            "label": "farmland",
            "polygon": [
                [
                    0,
                    347
                ],
                [
                    0,
                    384
                ],
                [
                    3,
                    347
                ]
            ]
        },
        {
            "label": "farmland",
            "polygon": [
                [
                    214,
                    328
                ],
                [
                    114,
                    318
                ],
                [
                    115,
                    337
                ],
                [
                    121,
                    340
                ],
                [
                    126,
                    342
                ],
                [
                    163,
                    342
                ],
                [
                    214,
                    340
                ]
            ]
        },
        {
            "label": "farmland",
            "polygon": [
                [
                    213,
                    313
                ],
                [
                    114,
                    304
                ],
                [
                    116,
                    314
                ],
                [
                    212,
                    323
                ]
            ]
        },
        {
            "label": "farmland",
            "polygon": [
                [
                    211,
                    298
                ],
                [
                    115,
                    290
                ],
                [
                    115,
                    301
                ],
                [
                    212,
                    308
                ]
            ]
        },
        {
            "label": "farmland",
            "polygon": [
                [
                    207,
                    243
                ],
                [
                    116,
                    242
                ],
                [
                    116,
                    287
                ],
                [
                    211,
                    296
                ],
                [
                    210,
                    264
                ]
            ]
        },
        {
            "label": "farmland",
            "polygon": [
                [
                    107,
                    340
                ],
                [
                    110,
                    251
                ],
                [
                    70,
                    251
                ],
                [
                    50,
                    256
                ],
                [
                    48,
                    339
                ]
            ]
        },
        {
            "label": "farmland",
            "polygon": [
                [
                    113,
                    245
                ],
                [
                    114,
                    238
                ],
                [
                    140,
                    238
                ],
                [
                    142,
                    217
                ],
                [
                    73,
                    204
                ],
                [
                    70,
                    247
                ]
            ]
        },
        {
            "label": "farmland",
            "polygon": [
                [
                    71,
                    202
                ],
                [
                    6,
                    189
                ],
                [
                    2,
                    244
                ],
                [
                    30,
                    244
                ],
                [
                    42,
                    247
                ],
                [
                    45,
                    251
                ],
                [
                    67,
                    249
                ]
            ]
        },
        {
            "label": "farmland",
            "polygon": [
                [
                    44,
                    338
                ],
                [
                    47,
                    260
                ],
                [
                    37,
                    261
                ],
                [
                    23,
                    275
                ],
                [
                    23,
                    339
                ]
            ]
        },
        {
            "label": "farmland",
            "polygon": [
                [
                    0,
                    260
                ],
                [
                    0,
                    342
                ],
                [
                    15,
                    343
                ],
                [
                    19,
                    263
                ],
                [
                    10,
                    260
                ]
            ]
        },
        {
            "label": "farmland",
            "polygon": [
                [
                    0,
                    78
                ],
                [
                    0,
                    121
                ],
                [
                    4,
                    78
                ]
            ]
        },
        {
            "label": "farmland",
            "polygon": [
                [
                    40,
                    85
                ],
                [
                    21,
                    84
                ],
                [
                    13,
                    137
                ],
                [
                    30,
                    138
                ]
            ]
        },
        {
            "label": "farmland",
            "polygon": [
                [
                    69,
                    88
                ],
                [
                    43,
                    83
                ],
                [
                    33,
                    151
                ],
                [
                    59,
                    155
                ]
            ]
        },
        {
            "label": "farmland",
            "polygon": [
                [
                    82,
                    160
                ],
                [
                    84,
                    152
                ],
                [
                    107,
                    158
                ],
                [
                    114,
                    158
                ],
                [
                    123,
                    99
                ],
                [
                    74,
                    90
                ],
                [
                    64,
                    149
                ],
                [
                    73,
                    150
                ],
                [
                    75,
                    158
                ]
            ]
        },
        {
            "label": "farmland",
            "polygon": [
                [
                    184,
                    110
                ],
                [
                    132,
                    101
                ],
                [
                    125,
                    159
                ],
                [
                    173,
                    169
                ]
            ]
        },
        {
            "label": "farmland",
            "polygon": [
                [
                    269,
                    121
                ],
                [
                    186,
                    110
                ],
                [
                    177,
                    168
                ],
                [
                    194,
                    170
                ],
                [
                    199,
                    176
                ],
                [
                    236,
                    181
                ],
                [
                    243,
                    187
                ],
                [
                    257,
                    190
                ]
            ]
        },
        {
            "label": "farmland",
            "polygon": [
                [
                    295,
                    128
                ],
                [
                    271,
                    124
                ],
                [
                    265,
                    179
                ],
                [
                    287,
                    183
                ]
            ]
        },
        {
            "label": "farmland",
            "polygon": [
                [
                    339,
                    133
                ],
                [
                    300,
                    127
                ],
                [
                    289,
                    199
                ],
                [
                    331,
                    206
                ]
            ]
        },
        {
            "label": "farmland",
            "polygon": [
                [
                    400,
                    139
                ],
                [
                    351,
                    135
                ],
                [
                    345,
                    207
                ],
                [
                    405,
                    221
                ]
            ]
        },
        {
            "label": "farmland",
            "polygon": [
                [
                    19,
                    0
                ],
                [
                    0,
                    0
                ],
                [
                    0,
                    72
                ],
                [
                    13,
                    75
                ]
            ]
        },
        {
            "label": "farmland",
            "polygon": [
                [
                    37,
                    0
                ],
                [
                    22,
                    0
                ],
                [
                    17,
                    74
                ],
                [
                    32,
                    75
                ]
            ]
        },
        {
            "label": "farmland",
            "polygon": [
                [
                    78,
                    0
                ],
                [
                    40,
                    0
                ],
                [
                    34,
                    77
                ],
                [
                    70,
                    83
                ]
            ]
        },
        {
            "label": "farmland",
            "polygon": [
                [
                    126,
                    0
                ],
                [
                    81,
                    0
                ],
                [
                    74,
                    82
                ],
                [
                    95,
                    88
                ],
                [
                    124,
                    90
                ],
                [
                    129,
                    49
                ],
                [
                    124,
                    16
                ]
            ]
        },
        {
            "label": "farmland",
            "polygon": [
                [
                    425,
                    218
                ],
                [
                    417,
                    131
                ],
                [
                    402,
                    132
                ],
                [
                    409,
                    218
                ]
            ]
        },
        {
            "label": "farmland",
            "polygon": [
                [
                    468,
                    235
                ],
                [
                    454,
                    131
                ],
                [
                    421,
                    132
                ],
                [
                    428,
                    221
                ],
                [
                    445,
                    222
                ],
                [
                    449,
                    230
                ]
            ]
        },
        {
            "label": "farmland",
            "polygon": [
                [
                    476,
                    133
                ],
                [
                    461,
                    132
                ],
                [
                    474,
                    235
                ],
                [
                    491,
                    238
                ]
            ]
        },
        {
            "label": "farmland",
            "polygon": [
                [
                    511,
                    237
                ],
                [
                    496,
                    131
                ],
                [
                    479,
                    131
                ],
                [
                    494,
                    239
                ],
                [
                    510,
                    240
                ]
            ]
        },
        {
            "label": "farmland",
            "polygon": [
                [
                    512,
                    130
                ],
                [
                    498,
                    131
                ],
                [
                    512,
                    231
                ]
            ]
        },
        {
            "label": "farmland",
            "polygon": [
                [
                    512,
                    126
                ],
                [
                    512,
                    46
                ],
                [
                    496,
                    49
                ],
                [
                    505,
                    127
                ]
            ]
        },
        {
            "label": "farmland",
            "polygon": [
                [
                    502,
                    127
                ],
                [
                    492,
                    50
                ],
                [
                    458,
                    52
                ],
                [
                    464,
                    128
                ]
            ]
        },
        {
            "label": "farmland",
            "polygon": [
                [
                    460,
                    127
                ],
                [
                    454,
                    52
                ],
                [
                    434,
                    53
                ],
                [
                    417,
                    52
                ],
                [
                    420,
                    128
                ],
                [
                    437,
                    127
                ]
            ]
        },
        {
            "label": "farmland",
            "polygon": [
                [
                    416,
                    55
                ],
                [
                    394,
                    55
                ],
                [
                    397,
                    129
                ],
                [
                    417,
                    126
                ]
            ]
        },
        {
            "label": "farmland",
            "polygon": [
                [
                    316,
                    48
                ],
                [
                    302,
                    46
                ],
                [
                    297,
                    117
                ],
                [
                    302,
                    118
                ],
                [
                    302,
                    123
                ],
                [
                    310,
                    122
                ]
            ]
        },
        {
            "label": "farmland",
            "polygon": [
                [
                    334,
                    48
                ],
                [
                    319,
                    47
                ],
                [
                    312,
                    122
                ],
                [
                    317,
                    124
                ],
                [
                    320,
                    127
                ],
                [
                    326,
                    127
                ]
            ]
        },
        {
            "label": "farmland",
            "polygon": [
                [
                    352,
                    49
                ],
                [
                    335,
                    48
                ],
                [
                    329,
                    126
                ],
                [
                    346,
                    127
                ]
            ]
        },
        {
            "label": "farmland",
            "polygon": [
                [
                    379,
                    52
                ],
                [
                    355,
                    49
                ],
                [
                    350,
                    130
                ],
                [
                    374,
                    133
                ]
            ]
        },
        {
            "label": "farmland",
            "polygon": [
                [
                    392,
                    53
                ],
                [
                    381,
                    52
                ],
                [
                    377,
                    132
                ],
                [
                    393,
                    134
                ]
            ]
        },
        {
            "label": "farmland",
            "polygon": [
                [
                    317,
                    0
                ],
                [
                    304,
                    0
                ],
                [
                    303,
                    42
                ],
                [
                    315,
                    43
                ]
            ]
        },
        {
            "label": "farmland",
            "polygon": [
                [
                    350,
                    0
                ],
                [
                    320,
                    0
                ],
                [
                    318,
                    43
                ],
                [
                    349,
                    46
                ]
            ]
        },
        {
            "label": "farmland",
            "polygon": [
                [
                    383,
                    0
                ],
                [
                    354,
                    0
                ],
                [
                    353,
                    47
                ],
                [
                    381,
                    49
                ]
            ]
        },
        {
            "label": "farmland",
            "polygon": [
                [
                    406,
                    0
                ],
                [
                    387,
                    0
                ],
                [
                    385,
                    48
                ],
                [
                    406,
                    50
                ]
            ]
        },
        {
            "label": "farmland",
            "polygon": [
                [
                    417,
                    0
                ],
                [
                    409,
                    0
                ],
                [
                    410,
                    49
                ],
                [
                    418,
                    50
                ]
            ]
        },
        {
            "label": "farmland",
            "polygon": [
                [
                    455,
                    0
                ],
                [
                    421,
                    0
                ],
                [
                    423,
                    49
                ],
                [
                    457,
                    49
                ],
                [
                    456,
                    17
                ]
            ]
        },
        {
            "label": "farmland",
            "polygon": [
                [
                    466,
                    0
                ],
                [
                    457,
                    0
                ],
                [
                    460,
                    47
                ],
                [
                    469,
                    47
                ]
            ]
        },
        {
            "label": "farmland",
            "polygon": [
                [
                    489,
                    0
                ],
                [
                    469,
                    0
                ],
                [
                    471,
                    46
                ],
                [
                    494,
                    46
                ]
            ]
        },
        {
            "label": "farmland",
            "polygon": [
                [
                    512,
                    41
                ],
                [
                    512,
                    0
                ],
                [
                    493,
                    0
                ],
                [
                    498,
                    45
                ]
            ]
        },
        {
            "label": "farmland",
            "polygon": [
                [
                    293,
                    100
                ],
                [
                    134,
                    83
                ],
                [
                    131,
                    93
                ],
                [
                    294,
                    112
                ]
            ]
        },
        {
            "label": "farmland",
            "polygon": [
                [
                    295,
                    90
                ],
                [
                    214,
                    79
                ],
                [
                    214,
                    88
                ],
                [
                    294,
                    97
                ]
            ]
        },
        {
            "label": "farmland",
            "polygon": [
                [
                    210,
                    78
                ],
                [
                    139,
                    70
                ],
                [
                    134,
                    73
                ],
                [
                    137,
                    80
                ],
                [
                    210,
                    88
                ]
            ]
        },
        {
            "label": "farmland",
            "polygon": [
                [
                    295,
                    77
                ],
                [
                    142,
                    59
                ],
                [
                    140,
                    68
                ],
                [
                    296,
                    86
                ]
            ]
        },
        {
            "label": "farmland",
            "polygon": [
                [
                    297,
                    60
                ],
                [
                    140,
                    40
                ],
                [
                    143,
                    56
                ],
                [
                    296,
                    75
                ]
            ]
        },
        {
            "label": "farmland",
            "polygon": [
                [
                    294,
                    21
                ],
                [
                    139,
                    4
                ],
                [
                    139,
                    22
                ],
                [
                    141,
                    37
                ],
                [
                    296,
                    57
                ],
                [
                    299,
                    28
                ],
                [
                    294,
                    26
                ]
            ]
        },
        {
            "label": "farmland",
            "polygon": [
                [
                    295,
                    0
                ],
                [
                    133,
                    0
                ],
                [
                    133,
                    1
                ],
                [
                    294,
                    19
                ]
            ]
        }
    ]
}