{
    "imgHeight": 512,
    "imgWidth": 512,
    "objects": [
        {
            "label": "farmland",
            "polygon": [
                [
                    0,
                    291
                ],
                [
                    0,
                    314
                ],
                [
                    2,
                    314
                ]
            ]
        },
        {
            "label": "farmland",
            "polygon": [
                [
                    0,
                    317
                ],
                [
                    0,
                    364
                ],
                [
                    2,
                    364
                ],
                [
                    12,
                    364
                ],
                [
                    12,
                    317
                ],
                [
                    10,
                    317
                ]
            ]
        },
        {
            "label": "farmland",
            "polygon": [
                [
                    50,
                    364
                ],
                [
                    49,
                    338
                ],
                [
                    15,
                    339
                ],
                [
                    15,
                    364
                ],
                [
                    17,
                    364
                ]
            ]
        },
        {
            "label": "farmland",
            "polygon": [
                [
                    46,
                    336
                ],
                [
                    46,
                    314
                ],
                [
                    15,
                    317
                ],
                [
                    14,
                    336
                ]
            ]
        },
        {
            "label": "farmland",
            "polygon": [
                [
                    36,
                    312
                ],
                [
                    33,
                    288
                ],
                [
                    3,
                    288
                ],
                [
                    5,
                    314
                ]
            ]
        },
        {
            "label": "farmland",
            "polygon": [
                [
                    66,
                    305
                ],
                [
                    66,
                    286
                ],
                [
                    37,
                    288
                ],
                [
                    40,
                    311
                ]
            ]
        },
        {
            "label": "farmland",
            "polygon": [
                [
                    58,
                    358
                ],
                [
                    56,
                    314
                ],
                [
                    51,
                    315
                ],
                [
                    52,
                    359
                ]
            ]
        },
        {
            "label": "farmland",
            "polygon": [
                [
                    83,
                    357
                ],
                [
                    81,
                    308
                ],
                [
                    60,
                    311
                ],
                [
                    61,
                    358
                ]
            ]
        },
        {
            "label": "farmland",
            "polygon": [
                [
                    101,
                    354
                ],
                [
                    98,
                    305
                ],
                [
                    83,
                    308
                ],
                [
                    85,
                    356
                ]
            ]
        },
        {
            "label": "farmland",
            "polygon": [
                [
                    133,
                    348
                ],
                [
                    129,
                    300
                ],
                [
                    101,
                    304
                ],
                [
                    105,
                    355
                ]
            ]
        },
        {
            "label": "farmland",
            "polygon": [
                [
                    0,
                    212
                ],
                [
                    0,
                    284
                ],
                [
                    56,
                    282
                ],
                [
                    55,
                    214
                ]
            ]
        },
        {
            "label": "farmland",
            "polygon": [
                [
                    89,
                    233
                ],
                [
                    64,
                    230
                ],
                [
                    70,
                    304
                ],
                [
                    95,
                    301
                ]
            ]
        },
        {
            "label": "farmland",
            "polygon": [
                [
                    105,
                    241
                ],
                [
                    92,
                    237
                ],
                [
                    98,
                    302
                ],
                [
                    111,
                    299
                ]
            ]
        },
        {
            "label": "farmland",
            "polygon": [
                [
                    118,
                    245
                ],
                [
                    110,
                    242
                ],
                [
                    114,
                    299
                ],
                [
                    120,
                    299
                ]
            ]
        },
        {
            "label": "farmland",
            "polygon": [
                [
                    125,
                    249
                ],
                [
                    122,
                    247
                ],
                [
                    124,
                    297
                ],
                [
                    128,
                    296
                ]
            ]
        },
        {
            "label": "farmland",
            "polygon": [
                [
                    0,
                    46
                ],
                [
                    0,
                    182
                ],
                [
                    8,
                    182
                ],
                [
                    5,
                    158
                ],
                [
                    50,
                    161
                ],
                [
                    49,
                    140
                ],
                [
                    42,
                    131
                ],
                [
                    49,
                    121
                ],
                [
                    49,
                    115
                ],
                [
                    22,
                    115
                ],
                [
                    22,
                    80
                ],
                [
                    29,
                    76
                ],
                [
                    29,
                    43
                ]
            ]
        },
        {
            "label": "farmland",
            "polygon": [
                [
                    0,
                    22
                ],
                [
                    0,
                    38
                ],
                [
                    31,
                    38
                ],
                [
                    31,
                    23
                ]
            ]
        },
        {
            "label": "farmland",
            "polygon": [
                [
                    43,
                    23
                ],
                [
                    37,
                    23
                ],
                [
                    38,
                    48
                ],
                [
                    33,
                    49
                ],
                [
                    33,
                    77
                ],
                [
                    26,
                    82
                ],
                [
                    26,
                    110
                ],
                [
                    48,
                    110
                ]
            ]
        },
        {
            "label": "farmland",
            "polygon": [
                [
                    66,
                    0
                ],
                [
                    44,
                    0
                ],
                [
                    45,
                    18
                ],
                [
                    64,
                    15
                ]
            ]
        },
        {
            "label": "farmland",
            "polygon": [
                [
                    64,
                    64
                ],
                [
                    63,
                    24
                ],
                [
                    48,
                    27
                ],
                [
                    49,
                    66
                ]
            ]
        },
        {
            "label": "farmland",
            "polygon": [
                [
                    116,
                    27
                ],
                [
                    104,
                    16
                ],
                [
                    92,
                    25
                ],
                [
                    95,
                    63
                ],
                [
                    118,
                    59
                ]
            ]
        },
        {
            "label": "farmland",
            "polygon": [
                [
                    118,
                    0
                ],
                [
                    68,
                    0
                ],
                [
                    67,
                    15
                ],
                [
                    118,
                    2
                ]
            ]
        },
        {
            "label": "farmland",
            "polygon": [
                [
                    130,
                    82
                ],
                [
                    127,
                    60
                ],
                [
                    53,
                    69
                ],
                [
                    55,
                    88
                ]
            ]
        },
        {
            "label": "farmland",
            "polygon": [
                [
                    132,
                    92
                ],
                [
                    131,
                    85
                ],
                [
                    56,
                    93
                ],
                [
                    57,
                    98
                ]
            ]
        },
        {
            "label": "farmland",
            "polygon": [
                [
                    137,
                    118
                ],
                [
                    133,
                    102
                ],
                [
                    58,
                    109
                ],
                [
                    57,
                    174
                ],
                [
                    131,
                    169
                ],
                [
                    135,
                    145
                ]
            ]
        },
        {
            "label": "farmland",
            "polygon": [
                [
                    128,
                    189
                ],
                [
                    130,
                    171
                ],
                [
                    60,
                    176
                ],
                [
                    59,
                    195
                ]
            ]
        },
        {
            "label": "farmland",
            "polygon": [
                [
                    126,
                    212
                ],
                [
                    127,
                    191
                ],
                [
                    61,
                    198
                ],
                [
                    60,
                    205
                ],
                [
                    66,
                    212
                ]
            ]
        },
        {
            "label": "farmland",
            "polygon": [
                [
                    127,
                    215
                ],
                [
                    69,
                    214
                ],
                [
                    70,
                    223
                ],
                [
                    74,
                    225
                ],
                [
                    84,
                    227
                ],
                [
                    85,
                    227
                ],
                [
                    119,
                    228
                ],
                [
                    126,
                    231
                ]
            ]
        },
        {
            "label": "farmland",
            "polygon": [
                [
                    125,
                    234
                ],
                [
                    121,
                    233
                ],
                [
                    92,
                    234
                ],
                [
                    92,
                    235
                ],
                [
                    110,
                    240
                ],
                [
                    128,
                    248
                ]
            ]
        },
        {
            "label": "farmland",
            "polygon": [
                [
                    279,
                    364
                ],
                [
                    272,
                    341
                ],
                [
                    174,
                    350
                ],
                [
                    175,
                    363
                ],
                [
                    189,
                    364
                ]
            ]
        },
        {
            "label": "farmland",
            "polygon": [
                [
                    301,
                    364
                ],
                [
                    298,
                    340
                ],
                [
                    278,
                    340
                ],
                [
                    281,
                    364
                ],
                [
                    284,
                    364
                ]
            ]
        },
        {
            "label": "farmland",
            "polygon": [
                [
                    321,
                    364
                ],
                [
                    314,
                    336
                ],
                [
                    301,
                    338
                ],
                [
                    304,
                    364
                ],
                [
                    307,
                    364
                ]
            ]
        },
        {
            "label": "farmland",
            "polygon": [
                [
                    172,
                    337
                ],
                [
                    141,
                    337
                ],
                [
                    140,
                    349
                ],
                [
                    172,
                    345
                ]
            ]
        },
        {
            "label": "farmland",
            "polygon": [
                [
                    171,
                    333
                ],
                [
                    171,
                    314
                ],
                [
                    138,
                    318
                ],
                [
                    139,
                    334
                ]
            ]
        },
        {
            "label": "farmland",
            "polygon": [
                [
                    170,
                    292
                ],
                [
                    170,
                    283
                ],
                [
                    136,
                    286
                ],
                [
                    135,
                    286
                ],
                [
                    136,
                    290
                ],
                [
                    138,
                    294
                ]
            ]
        },
        {
            "label": "farmland",
            "polygon": [
                [
                    152,
                    272
                ],
                [
                    151,
                    247
                ],
                [
                    133,
                    248
                ],
                [
                    136,
                    283
                ],
                [
                    170,
                    280
                ],
                [
                    169,
                    273
                ]
            ]
        },
        {
            "label": "farmland",
            "polygon": [
                [
                    170,
                    311
                ],
                [
                    171,
                    295
                ],
                [
                    138,
                    297
                ],
                [
                    139,
                    315
                ]
            ]
        },
        {
            "label": "farmland",
            "polygon": [
                [
                    228,
                    273
                ],
                [
                    214,
                    269
                ],
                [
                    196,
                    275
                ],
                [
                    175,
                    279
                ],
                [
                    175,
                    345
                ],
                [
                    275,
                    331
                ],
                [
                    273,
                    304
                ],
                [
                    269,
                    303
                ],
                [
                    263,
                    296
                ],
                [
                    253,
                    289
                ]
            ]
        },
        {
            "label": "farmland",
            "polygon": [
                [
                    309,
                    315
                ],
                [
                    294,
                    312
                ],
                [
                    281,
                    324
                ],
                [
                    279,
                    332
                ],
                [
                    314,
                    329
                ]
            ]
        },
        {
            "label": "farmland",
            "polygon": [
                [
                    177,
                    274
                ],
                [
                    175,
                    245
                ],
                [
                    157,
                    247
                ],
                [
                    158,
                    269
                ],
                [
                    171,
                    268
                ],
                [
                    173,
                    274
                ]
            ]
        },
        {
            "label": "farmland",
            "polygon": [
                [
                    185,
                    245
                ],
                [
                    178,
                    244
                ],
                [
                    180,
                    267
                ],
                [
                    188,
                    268
                ],
                [
                    189,
                    272
                ],
                [
                    206,
                    265
                ],
                [
                    207,
                    264
                ],
                [
                    202,
                    259
                ],
                [
                    194,
                    252
                ]
            ]
        },
        {
            "label": "farmland",
            "polygon": [
                [
                    160,
                    200
                ],
                [
                    135,
                    198
                ],
                [
                    133,
                    219
                ],
                [
                    133,
                    235
                ],
                [
                    159,
                    232
                ]
            ]
        },
        {
            "label": "farmland",
            "polygon": [
                [
                    231,
                    241
                ],
                [
                    246,
                    221
                ],
                [
                    194,
                    210
                ],
                [
                    168,
                    206
                ],
                [
                    167,
                    241
                ],
                [
                    180,
                    239
                ],
                [
                    181,
                    224
                ],
                [
                    184,
                    224
                ],
                [
                    207,
                    230
                ]
            ]
        },
        {
            "label": "farmland",
            "polygon": [
                [
                    196,
                    230
                ],
                [
                    184,
                    227
                ],
                [
                    185,
                    235
                ],
                [
                    189,
                    239
                ],
                [
                    199,
                    244
                ],
                [
                    219,
                    255
                ],
                [
                    228,
                    245
                ]
            ]
        },
        {
            "label": "farmland",
            "polygon": [
                [
                    216,
                    257
                ],
                [
                    184,
                    238
                ],
                [
                    183,
                    242
                ],
                [
                    197,
                    250
                ],
                [
                    206,
                    259
                ],
                [
                    210,
                    265
                ]
            ]
        },
        {
            "label": "farmland",
            "polygon": [
                [
                    267,
                    229
                ],
                [
                    251,
                    225
                ],
                [
                    218,
                    264
                ],
                [
                    264,
                    292
                ],
                [
                    269,
                    296
                ],
                [
                    274,
                    302
                ],
                [
                    280,
                    303
                ],
                [
                    282,
                    297
                ],
                [
                    286,
                    244
                ],
                [
                    285,
                    231
                ]
            ]
        },
        {
            "label": "farmland",
            "polygon": [
                [
                    302,
                    292
                ],
                [
                    297,
                    230
                ],
                [
                    289,
                    231
                ],
                [
                    290,
                    247
                ],
                [
                    284,
                    300
                ],
                [
                    281,
                    308
                ],
                [
                    310,
                    312
                ]
            ]
        },
        {
            "label": "farmland",
            "polygon": [
                [
                    273,
                    206
                ],
                [
                    269,
                    203
                ],
                [
                    255,
                    220
                ],
                [
                    269,
                    225
                ],
                [
                    283,
                    228
                ],
                [
                    293,
                    221
                ],
                [
                    295,
                    216
                ],
                [
                    291,
                    207
                ],
                [
                    286,
                    206
                ]
            ]
        },
        {
            "label": "farmland",
            "polygon": [
                [
                    262,
                    196
                ],
                [
                    258,
                    178
                ],
                [
                    206,
                    186
                ],
                [
                    206,
                    189
                ],
                [
                    207,
                    203
                ],
                [
                    208,
                    207
                ],
                [
                    228,
                    207
                ],
                [
                    238,
                    211
                ],
                [
                    248,
                    210
                ],
                [
                    253,
                    205
                ]
            ]
        },
        {
            "label": "farmland",
            "polygon": [
                [
                    288,
                    197
                ],
                [
                    280,
                    174
                ],
                [
                    261,
                    178
                ],
                [
                    267,
                    196
                ],
                [
                    276,
                    198
                ],
                [
                    280,
                    199
                ],
                [
                    285,
                    198
                ]
            ]
        },
        {
            "label": "farmland",
            "polygon": [
                [
                    201,
                    167
                ],
                [
                    140,
                    161
                ],
                [
                    136,
                    194
                ],
                [
                    163,
                    196
                ],
                [
                    164,
                    201
                ],
                [
                    185,
                    202
                ],
                [
                    204,
                    207
                ]
            ]
        },
        {
            "label": "farmland",
            "polygon": [
                [
                    279,
                    171
                ],
                [
                    271,
                    130
                ],
                [
                    207,
                    141
                ],
                [
                    208,
                    182
                ]
            ]
        },
        {
            "label": "farmland",
            "polygon": [
                [
                    271,
                    127
                ],
                [
                    271,
                    116
                ],
                [
                    205,
                    129
                ],
                [
                    205,
                    138
                ]
            ]
        },
        {
            "label": "farmland",
            "polygon": [
                [
                    198,
                    156
                ],
                [
                    142,
                    149
                ],
                [
                    141,
                    158
                ],
                [
                    198,
                    164
                ]
            ]
        },
        {
            "label": "farmland",
            "polygon": [
                [
                    196,
                    128
                ],
                [
                    144,
                    124
                ],
                [
                    143,
                    146
                ],
                [
                    198,
                    152
                ]
            ]
        },
        {
            "label": "farmland",
            "polygon": [
                [
                    197,
                    125
                ],
                [
                    192,
                    83
                ],
                [
                    142,
                    92
                ],
                [
                    144,
                    119
                ]
            ]
        },
        {
            "label": "farmland",
            "polygon": [
                [
                    267,
                    98
                ],
                [
                    261,
                    83
                ],
                [
                    202,
                    96
                ],
                [
                    203,
                    126
                ],
                [
                    272,
                    113
                ]
            ]
        },
        {
            "label": "farmland",
            "polygon": [
                [
                    258,
                    82
                ],
                [
                    254,
                    68
                ],
                [
                    199,
                    79
                ],
                [
                    200,
                    94
                ]
            ]
        },
        {
            "label": "farmland",
            "polygon": [
                [
                    192,
                    79
                ],
                [
                    190,
                    54
                ],
                [
                    135,
                    62
                ],
                [
                    138,
                    88
                ]
            ]
        },
        {
            "label": "farmland",
            "polygon": [
                [
                    253,
                    56
                ],
                [
                    248,
                    45
                ],
                [
                    244,
                    50
                ],
                [
                    237,
                    51
                ],
                [
                    198,
                    55
                ],
                [
                    199,
                    77
                ],
                [
                    253,
                    66
                ]
            ]
        },
        {
            "label": "farmland",
            "polygon": [
                [
                    329,
                    345
                ],
                [
                    353,
                    341
                ],
                [
                    349,
                    332
                ],
                [
                    349,
                    331
                ],
                [
                    323,
                    334
                ],
                [
                    327,
                    345
                ]
            ]
        },
        {
            "label": "farmland",
            "polygon": [
                [
                    329,
                    345
                ],
                [
                    329,
                    353
                ],
                [
                    348,
                    360
                ],
                [
                    357,
                    351
                ],
                [
                    354,
                    343
                ]
            ]
        },
        {
            "label": "farmland",
            "polygon": [
                [
                    349,
                    332
                ],
                [
                    360,
                    353
                ],
                [
                    374,
                    346
                ],
                [
                    364,
                    329
                ]
            ]
        },
        {
            "label": "farmland",
            "polygon": [
                [
                    428,
                    364
                ],
                [
                    405,
                    322
                ],
                [
                    367,
                    326
                ],
                [
                    378,
                    344
                ],
                [
                    378,
                    364
                ]
            ]
        },
        {
            "label": "farmland",
            "polygon": [
                [
                    450,
                    332
                ],
                [
                    441,
                    315
                ],
                [
                    408,
                    321
                ],
                [
                    428,
                    356
                ],
                [
                    432,
                    353
                ],
                [
                    440,
                    348
                ],
                [
                    441,
                    348
                ],
                [
                    449,
                    341
                ]
            ]
        },
        {
            "label": "farmland",
            "polygon": [
                [
                    512,
                    353
                ],
                [
                    495,
                    326
                ],
                [
                    497,
                    309
                ],
                [
                    445,
                    315
                ],
                [
                    445,
                    316
                ],
                [
                    453,
                    332
                ],
                [
                    454,
                    341
                ],
                [
                    446,
                    351
                ],
                [
                    432,
                    362
                ],
                [
                    434,
                    364
                ],
                [
                    512,
                    364
                ]
            ]
        },
        {
            "label": "farmland",
            "polygon": [
                [
                    512,
                    327
                ],
                [
                    500,
                    327
                ],
                [
                    512,
                    346
                ]
            ]
        },
        {
            "label": "farmland",
            "polygon": [
                [
                    512,
                    305
                ],
                [
                    501,
                    306
                ],
                [
                    500,
                    321
                ],
                [
                    512,
                    323
                ]
            ]
        },
        {
            "label": "farmland",
            "polygon": [
                [
                    353,
                    309
                ],
                [
                    337,
                    286
                ],
                [
                    327,
                    288
                ],
                [
                    312,
                    296
                ],
                [
                    323,
                    326
                ],
                [
                    362,
                    321
                ]
            ]
        },
        {
            "label": "farmland",
            "polygon": [
                [
                    325,
                    283
                ],
                [
                    323,
                    256
                ],
                [
                    304,
                    256
                ],
                [
                    305,
                    289
                ],
                [
                    313,
                    291
                ]
            ]
        },
        {
            "label": "farmland",
            "polygon": [
                [
                    352,
                    243
                ],
                [
                    337,
                    212
                ],
                [
                    320,
                    214
                ],
                [
                    302,
                    219
                ],
                [
                    303,
                    231
                ],
                [
                    305,
                    253
                ],
                [
                    335,
                    250
                ]
            ]
        },
        {
            "label": "farmland",
            "polygon": [
                [
                    342,
                    275
                ],
                [
                    349,
                    275
                ],
                [
                    351,
                    275
                ],
                [
                    365,
                    266
                ],
                [
                    351,
                    246
                ],
                [
                    337,
                    253
                ],
                [
                    326,
                    255
                ],
                [
                    330,
                    277
                ]
            ]
        },
        {
            "label": "farmland",
            "polygon": [
                [
                    462,
                    305
                ],
                [
                    460,
                    289
                ],
                [
                    455,
                    276
                ],
                [
                    446,
                    259
                ],
                [
                    420,
                    259
                ],
                [
                    401,
                    259
                ],
                [
                    392,
                    247
                ],
                [
                    390,
                    233
                ],
                [
                    367,
                    211
                ],
                [
                    342,
                    211
                ],
                [
                    356,
                    243
                ],
                [
                    369,
                    268
                ],
                [
                    357,
                    275
                ],
                [
                    365,
                    289
                ],
                [
                    399,
                    283
                ],
                [
                    402,
                    294
                ],
                [
                    435,
                    292
                ],
                [
                    444,
                    309
                ]
            ]
        },
        {
            "label": "farmland",
            "polygon": [
                [
                    366,
                    298
                ],
                [
                    352,
                    277
                ],
                [
                    337,
                    278
                ],
                [
                    336,
                    280
                ],
                [
                    355,
                    307
                ]
            ]
        },
        {
            "label": "farmland",
            "polygon": [
                [
                    378,
                    317
                ],
                [
                    367,
                    300
                ],
                [
                    357,
                    308
                ],
                [
                    365,
                    320
                ]
            ]
        },
        {
            "label": "farmland",
            "polygon": [
                [
                    403,
                    313
                ],
                [
                    399,
                    306
                ],
                [
                    378,
                    310
                ],
                [
                    382,
                    317
                ]
            ]
        },
        {
            "label": "farmland",
            "polygon": [
                [
                    440,
                    310
                ],
                [
                    433,
                    297
                ],
                [
                    399,
                    299
                ],
                [
                    395,
                    289
                ],
                [
                    379,
                    292
                ],
                [
                    366,
                    292
                ],
                [
                    376,
                    308
                ],
                [
                    400,
                    303
                ],
                [
                    407,
                    313
                ]
            ]
        },
        {
            "label": "farmland",
            "polygon": [
                [
                    362,
                    196
                ],
                [
                    357,
                    184
                ],
                [
                    335,
                    187
                ],
                [
                    339,
                    207
                ],
                [
                    366,
                    206
                ]
            ]
        },
        {
            "label": "farmland",
            "polygon": [
                [
                    334,
                    168
                ],
                [
                    335,
                    169
                ],
                [
                    335,
                    170
                ],
                [
                    335,
                    172
                ],
                [
                    335,
                    171
                ],
                [
                    335,
                    183
                ],
                [
                    358,
                    180
                ],
                [
                    351,
                    143
                ],
                [
                    328,
                    145
                ],
                [
                    331,
                    155
                ]
            ]
        },
        {
            "label": "farmland",
            "polygon": [
                [
                    335,
                    170
                ],
                [
                    334,
                    168
                ],
                [
                    332,
                    165
                ],
                [
                    335,
                    171
                ]
            ]
        },
        {
            "label": "farmland",
            "polygon": [
                [
                    324,
                    161
                ],
                [
                    317,
                    135
                ],
                [
                    284,
                    142
                ],
                [
                    285,
                    166
                ]
            ]
        },
        {
            "label": "farmland",
            "polygon": [
                [
                    352,
                    138
                ],
                [
                    346,
                    97
                ],
                [
                    280,
                    111
                ],
                [
                    278,
                    136
                ],
                [
                    327,
                    126
                ],
                [
                    329,
                    138
                ]
            ]
        },
        {
            "label": "farmland",
            "polygon": [
                [
                    322,
                    98
                ],
                [
                    316,
                    85
                ],
                [
                    272,
                    96
                ],
                [
                    277,
                    108
                ]
            ]
        },
        {
            "label": "farmland",
            "polygon": [
                [
                    314,
                    79
                ],
                [
                    311,
                    74
                ],
                [
                    269,
                    84
                ],
                [
                    272,
                    91
                ]
            ]
        },
        {
            "label": "farmland",
            "polygon": [
                [
                    333,
                    51
                ],
                [
                    329,
                    43
                ],
                [
                    309,
                    49
                ],
                [
                    326,
                    98
                ],
                [
                    344,
                    94
                ]
            ]
        },
        {
            "label": "farmland",
            "polygon": [
                [
                    268,
                    82
                ],
                [
                    311,
                    70
                ],
                [
                    313,
                    70
                ],
                [
                    303,
                    48
                ],
                [
                    327,
                    39
                ],
                [
                    319,
                    22
                ],
                [
                    255,
                    46
                ],
                [
                    259,
                    54
                ],
                [
                    261,
                    62
                ],
                [
                    259,
                    72
                ]
            ]
        },
        {
            "label": "farmland",
            "polygon": [
                [
                    317,
                    20
                ],
                [
                    315,
                    14
                ],
                [
                    253,
                    39
                ],
                [
                    255,
                    44
                ]
            ]
        },
        {
            "label": "farmland",
            "polygon": [
                [
                    309,
                    0
                ],
                [
                    261,
                    0
                ],
                [
                    236,
                    12
                ],
                [
                    251,
                    38
                ],
                [
                    315,
                    11
                ]
            ]
        },
        {
            "label": "farmland",
            "polygon": [
                [
                    254,
                    0
                ],
                [
                    228,
                    0
                ],
                [
                    234,
                    10
                ]
            ]
        },
        {
            "label": "farmland",
            "polygon": [
                [
                    512,
                    296
                ],
                [
                    512,
                    264
                ],
                [
                    458,
                    273
                ],
                [
                    465,
                    287
                ],
                [
                    467,
                    303
                ]
            ]
        },
        {
            "label": "farmland",
            "polygon": [
                [
                    512,
                    257
                ],
                [
                    512,
                    136
                ],
                [
                    505,
                    94
                ],
                [
                    356,
                    126
                ],
                [
                    367,
                    185
                ],
                [
                    377,
                    207
                ],
                [
                    396,
                    228
                ],
                [
                    403,
                    247
                ],
                [
                    409,
                    250
                ],
                [
                    457,
                    253
                ],
                [
                    461,
                    263
                ]
            ]
        },
        {
            "label": "farmland",
            "polygon": [
                [
                    486,
                    0
                ],
                [
                    318,
                    0
                ],
                [
                    330,
                    17
                ],
                [
                    346,
                    57
                ],
                [
                    355,
                    94
                ],
                [
                    358,
                    118
                ],
                [
                    501,
                    87
                ]
            ]
        },
        {
            "label": "farmland",
            "polygon": [
                [
                    512,
                    91
                ],
                [
                    512,
                    0
                ],
                [
                    498,
                    0
                ],
                [
                    511,
                    91
                ]
            ]
        }
    ]
}