{
    "imgHeight": 512,
    "imgWidth": 512,
    "objects": [
        {
            "label": "farmland",
            "polygon": [
                [
                    87,
                    512
                ],
                [
                    211,
                    512
                ],
                [
                    216,
                    506
                ],
                [
                    229,
                    497
                ],
                [
                    243,
                    469
                ],
                [
                    255,
                    457
                ],
                [
                    252,
                    448
                ],
                [
                    271,
                    435
                ],
                [
                    264,
                    359
                ],
                [
                    258,
                    355
                ],
                [
                    176,
                    429
                ],
                [
                    175,
                    422
                ],
                [
                    134,
                    458
                ],
                [
                    116,
                    470
                ],
                [
                    85,
                    510
                ]
            ]
        },
        {
            "label": "farmland",
            "polygon": [
                [
                    285,
                    512
                ],
                [
                    443,
                    512
                ],
                [
                    449,
                    503
                ],
                [
                    346,
                    417
                ],
                [
                    272,
                    502
                ]
            ]
        },
        {
            "label": "farmland",
            "polygon": [
                [
                    442,
                    286
                ],
                [
                    372,
                    229
                ],
                [
                    365,
                    231
                ],
                [
                    309,
                    297
                ],
                [
                    290,
                    326
                ],
                [
                    288,
                    381
                ],
                [
                    295,
                    442
                ],
                [
                    303,
                    448
                ],
                [
                    353,
                    394
                ],
                [
                    377,
                    366
                ]
            ]
        },
        {
            "label": "farmland",
            "polygon": [
                [
                    512,
                    405
                ],
                [
                    512,
                    393
                ],
                [
                    427,
                    323
                ],
                [
                    357,
                    408
                ],
                [
                    456,
                    486
                ]
            ]
        },
        {
            "label": "farmland",
            "polygon": [
                [
                    454,
                    512
                ],
                [
                    458,
                    512
                ],
                [
                    456,
                    510
                ]
            ]
        },
        {
            "label": "farmland",
            "polygon": [
                [
                    464,
                    512
                ],
                [
                    500,
                    512
                ],
                [
                    471,
                    494
                ],
                [
                    459,
                    508
                ]
            ]
        },
        {
            "label": "farmland",
            "polygon": [
                [
                    512,
                    473
                ],
                [
                    486,
                    455
                ],
                [
                    472,
                    472
                ],
                [
                    483,
                    483
                ],
                [
                    475,
                    493
                ],
                [
                    504,
                    512
                ],
                [
                    512,
                    512
                ]
            ]
        },
        {
            "label": "farmland",
            "polygon": [
                [
                    512,
                    421
                ],
                [
                    491,
                    451
                ],
                [
                    491,
                    455
                ],
                [
                    512,
                    470
                ]
            ]
        },
        {
            "label": "farmland",
            "polygon": [
                [
                    512,
                    342
                ],
                [
                    497,
                    334
                ],
                [
                    477,
                    363
                ],
                [
                    512,
                    388
                ]
            ]
        },
        {
            "label": "farmland",
            "polygon": [
                [
                    512,
                    319
                ],
                [
                    503,
                    313
                ],
                [
                    494,
                    326
                ],
                [
                    512,
                    339
                ]
            ]
        },
        {
            "label": "farmland",
            "polygon": [
                [
                    512,
                    300
                ],
                [
                    506,
                    297
                ],
                [
                    499,
                    308
                ],
                [
                    512,
                    316
                ]
            ]
        },
        {
            "label": "farmland",
            "polygon": [
                [
                    495,
                    331
                ],
                [
                    474,
                    315
                ],
                [
                    468,
                    317
                ],
                [
                    443,
                    301
                ],
                [
                    429,
                    321
                ],
                [
                    451,
                    339
                ],
                [
                    476,
                    359
                ]
            ]
        },
        {
            "label": "farmland",
            "polygon": [
                [
                    504,
                    296
                ],
                [
                    468,
                    273
                ],
                [
                    452,
                    292
                ],
                [
                    475,
                    309
                ],
                [
                    491,
                    322
                ],
                [
                    498,
                    312
                ],
                [
                    495,
                    310
                ]
            ]
        },
        {
            "label": "farmland",
            "polygon": [
                [
                    512,
                    227
                ],
                [
                    512,
                    215
                ],
                [
                    468,
                    268
                ],
                [
                    476,
                    275
                ]
            ]
        },
        {
            "label": "farmland",
            "polygon": [
                [
                    512,
                    256
                ],
                [
                    512,
                    230
                ],
                [
                    479,
                    274
                ],
                [
                    494,
                    283
                ]
            ]
        },
        {
            "label": "farmland",
            "polygon": [
                [
                    512,
                    260
                ],
                [
                    502,
                    274
                ],
                [
                    512,
                    280
                ]
            ]
        },
        {
            "label": "farmland",
            "polygon": [
                [
                    0,
                    436
                ],
                [
                    0,
                    456
                ],
                [
                    43,
                    479
                ],
                [
                    54,
                    472
                ],
                [
                    84,
                    435
                ],
                [
                    29,
                    394
                ]
            ]
        },
        {
            "label": "farmland",
            "polygon": [
                [
                    109,
                    416
                ],
                [
                    46,
                    369
                ],
                [
                    31,
                    392
                ],
                [
                    87,
                    434
                ]
            ]
        },
        {
            "label": "farmland",
            "polygon": [
                [
                    208,
                    340
                ],
                [
                    114,
                    275
                ],
                [
                    48,
                    367
                ],
                [
                    113,
                    414
                ],
                [
                    127,
                    403
                ],
                [
                    135,
                    398
                ],
                [
                    145,
                    393
                ],
                [
                    186,
                    356
                ]
            ]
        },
        {
            "label": "farmland",
            "polygon": [
                [
                    168,
                    262
                ],
                [
                    159,
                    255
                ],
                [
                    154,
                    255
                ],
                [
                    149,
                    261
                ],
                [
                    133,
                    250
                ],
                [
                    116,
                    273
                ],
                [
                    209,
                    338
                ],
                [
                    231,
                    322
                ],
                [
                    221,
                    315
                ],
                [
                    224,
                    307
                ],
                [
                    223,
                    296
                ],
                [
                    193,
                    277
                ],
                [
                    184,
                    268
                ]
            ]
        },
        {
            "label": "farmland",
            "polygon": [
                [
                    0,
                    279
                ],
                [
                    0,
                    430
                ],
                [
                    78,
                    317
                ],
                [
                    21,
                    268
                ],
                [
                    16,
                    273
                ],
                [
                    10,
                    271
                ]
            ]
        },
        {
            "label": "farmland",
            "polygon": [
                [
                    0,
                    230
                ],
                [
                    0,
                    244
                ],
                [
                    47,
                    285
                ],
                [
                    69,
                    258
                ],
                [
                    107,
                    220
                ],
                [
                    99,
                    207
                ],
                [
                    96,
                    194
                ],
                [
                    83,
                    188
                ],
                [
                    77,
                    188
                ],
                [
                    69,
                    180
                ],
                [
                    65,
                    172
                ],
                [
                    58,
                    161
                ]
            ]
        },
        {
            "label": "farmland",
            "polygon": [
                [
                    124,
                    229
                ],
                [
                    108,
                    221
                ],
                [
                    49,
                    287
                ],
                [
                    82,
                    312
                ],
                [
                    130,
                    246
                ],
                [
                    122,
                    237
                ],
                [
                    125,
                    232
                ]
            ]
        },
        {
            "label": "farmland",
            "polygon": [
                [
                    275,
                    273
                ],
                [
                    306,
                    244
                ],
                [
                    318,
                    225
                ],
                [
                    280,
                    199
                ],
                [
                    258,
                    224
                ],
                [
                    260,
                    228
                ],
                [
                    236,
                    263
                ],
                [
                    242,
                    271
                ],
                [
                    264,
                    269
                ]
            ]
        },
        {
            "label": "farmland",
            "polygon": [
                [
                    277,
                    196
                ],
                [
                    222,
                    157
                ],
                [
                    163,
                    215
                ],
                [
                    186,
                    233
                ],
                [
                    212,
                    251
                ],
                [
                    221,
                    262
                ],
                [
                    226,
                    261
                ]
            ]
        },
        {
            "label": "farmland",
            "polygon": [
                [
                    330,
                    213
                ],
                [
                    240,
                    143
                ],
                [
                    224,
                    156
                ],
                [
                    320,
                    224
                ],
                [
                    326,
                    221
                ]
            ]
        },
        {
            "label": "farmland",
            "polygon": [
                [
                    366,
                    166
                ],
                [
                    300,
                    106
                ],
                [
                    245,
                    143
                ],
                [
                    331,
                    211
                ],
                [
                    334,
                    200
                ],
                [
                    341,
                    197
                ],
                [
                    362,
                    171
                ]
            ]
        },
        {
            "label": "farmland",
            "polygon": [
                [
                    344,
                    85
                ],
                [
                    341,
                    79
                ],
                [
                    304,
                    105
                ],
                [
                    367,
                    164
                ],
                [
                    383,
                    150
                ],
                [
                    396,
                    129
                ],
                [
                    370,
                    107
                ],
                [
                    366,
                    97
                ],
                [
                    355,
                    92
                ]
            ]
        },
        {
            "label": "farmland",
            "polygon": [
                [
                    284,
                    0
                ],
                [
                    271,
                    0
                ],
                [
                    220,
                    37
                ],
                [
                    269,
                    118
                ],
                [
                    278,
                    114
                ],
                [
                    340,
                    75
                ],
                [
                    328,
                    53
                ],
                [
                    300,
                    43
                ],
                [
                    284,
                    26
                ],
                [
                    293,
                    7
                ]
            ]
        },
        {
            "label": "farmland",
            "polygon": [
                [
                    265,
                    121
                ],
                [
                    216,
                    41
                ],
                [
                    171,
                    72
                ],
                [
                    184,
                    90
                ],
                [
                    202,
                    110
                ],
                [
                    228,
                    143
                ],
                [
                    237,
                    141
                ]
            ]
        },
        {
            "label": "farmland",
            "polygon": [
                [
                    212,
                    128
                ],
                [
                    169,
                    73
                ],
                [
                    77,
                    141
                ],
                [
                    93,
                    147
                ],
                [
                    105,
                    168
                ],
                [
                    133,
                    186
                ]
            ]
        },
        {
            "label": "farmland",
            "polygon": [
                [
                    225,
                    148
                ],
                [
                    214,
                    130
                ],
                [
                    134,
                    189
                ],
                [
                    162,
                    211
                ],
                [
                    222,
                    154
                ]
            ]
        },
        {
            "label": "farmland",
            "polygon": [
                [
                    0,
                    186
                ],
                [
                    0,
                    210
                ],
                [
                    12,
                    196
                ]
            ]
        },
        {
            "label": "farmland",
            "polygon": [
                [
                    0,
                    106
                ],
                [
                    0,
                    184
                ],
                [
                    17,
                    198
                ],
                [
                    54,
                    153
                ]
            ]
        },
        {
            "label": "farmland",
            "polygon": [
                [
                    118,
                    73
                ],
                [
                    103,
                    57
                ],
                [
                    56,
                    100
                ],
                [
                    30,
                    125
                ],
                [
                    42,
                    135
                ],
                [
                    60,
                    145
                ],
                [
                    102,
                    111
                ],
                [
                    128,
                    90
                ]
            ]
        },
        {
            "label": "farmland",
            "polygon": [
                [
                    0,
                    58
                ],
                [
                    0,
                    99
                ],
                [
                    27,
                    121
                ],
                [
                    83,
                    71
                ],
                [
                    62,
                    47
                ],
                [
                    63,
                    44
                ],
                [
                    37,
                    19
                ],
                [
                    15,
                    43
                ],
                [
                    10,
                    45
                ]
            ]
        },
        {
            "label": "farmland",
            "polygon": [
                [
                    92,
                    64
                ],
                [
                    72,
                    40
                ],
                [
                    64,
                    47
                ],
                [
                    83,
                    71
                ]
            ]
        },
        {
            "label": "farmland",
            "polygon": [
                [
                    38,
                    0
                ],
                [
                    31,
                    0
                ],
                [
                    38,
                    7
                ],
                [
                    34,
                    14
                ],
                [
                    62,
                    42
                ],
                [
                    70,
                    37
                ]
            ]
        },
        {
            "label": "farmland",
            "polygon": [
                [
                    54,
                    0
                ],
                [
                    40,
                    0
                ],
                [
                    71,
                    36
                ],
                [
                    80,
                    30
                ]
            ]
        },
        {
            "label": "farmland",
            "polygon": [
                [
                    102,
                    55
                ],
                [
                    82,
                    32
                ],
                [
                    73,
                    39
                ],
                [
                    93,
                    61
                ]
            ]
        },
        {
            "label": "farmland",
            "polygon": [
                [
                    118,
                    50
                ],
                [
                    93,
                    23
                ],
                [
                    84,
                    31
                ],
                [
                    108,
                    57
                ],
                [
                    116,
                    54
                ]
            ]
        },
        {
            "label": "farmland",
            "polygon": [
                [
                    74,
                    0
                ],
                [
                    58,
                    0
                ],
                [
                    81,
                    27
                ],
                [
                    91,
                    20
                ],
                [
                    87,
                    15
                ],
                [
                    76,
                    3
                ]
            ]
        },
        {
            "label": "farmland",
            "polygon": [
                [
                    91,
                    0
                ],
                [
                    78,
                    0
                ],
                [
                    83,
                    7
                ],
                [
                    87,
                    9
                ],
                [
                    94,
                    5
                ]
            ]
        },
        {
            "label": "farmland",
            "polygon": [
                [
                    129,
                    43
                ],
                [
                    98,
                    5
                ],
                [
                    88,
                    13
                ],
                [
                    120,
                    49
                ]
            ]
        },
        {
            "label": "farmland",
            "polygon": [
                [
                    101,
                    0
                ],
                [
                    95,
                    0
                ],
                [
                    96,
                    3
                ]
            ]
        },
        {
            "label": "farmland",
            "polygon": [
                [
                    115,
                    0
                ],
                [
                    109,
                    0
                ],
                [
                    100,
                    5
                ],
                [
                    130,
                    40
                ],
                [
                    141,
                    33
                ]
            ]
        },
        {
            "label": "farmland",
            "polygon": [
                [
                    128,
                    0
                ],
                [
                    117,
                    0
                ],
                [
                    143,
                    31
                ],
                [
                    150,
                    26
                ]
            ]
        },
        {
            "label": "farmland",
            "polygon": [
                [
                    151,
                    0
                ],
                [
                    133,
                    0
                ],
                [
                    152,
                    24
                ],
                [
                    165,
                    17
                ]
            ]
        },
        {
            "label": "farmland",
            "polygon": [
                [
                    165,
                    0
                ],
                [
                    154,
                    0
                ],
                [
                    169,
                    20
                ],
                [
                    177,
                    15
                ]
            ]
        },
        {
            "label": "farmland",
            "polygon": [
                [
                    188,
                    0
                ],
                [
                    168,
                    0
                ],
                [
                    178,
                    13
                ],
                [
                    192,
                    5
                ]
            ]
        },
        {
            "label": "farmland",
            "polygon": [
                [
                    197,
                    0
                ],
                [
                    190,
                    0
                ],
                [
                    193,
                    4
                ]
            ]
        },
        {
            "label": "farmland",
            "polygon": [
                [
                    172,
                    25
                ],
                [
                    162,
                    23
                ],
                [
                    111,
                    60
                ],
                [
                    132,
                    88
                ],
                [
                    189,
                    48
                ]
            ]
        },
        {
            "label": "farmland",
            "polygon": [
                [
                    259,
                    0
                ],
                [
                    204,
                    0
                ],
                [
                    186,
                    13
                ],
                [
                    174,
                    24
                ],
                [
                    191,
                    47
                ],
                [
                    249,
                    8
                ]
            ]
        },
        {
            "label": "farmland",
            "polygon": [
                [
                    29,
                    0
                ],
                [
                    0,
                    0
                ],
                [
                    0,
                    55
                ],
                [
                    11,
                    41
                ],
                [
                    35,
                    19
                ],
                [
                    32,
                    13
                ],
                [
                    36,
                    8
                ]
            ]
        },
        {
            "label": "farmland",
            "polygon": [
                [
                    480,
                    177
                ],
                [
                    443,
                    150
                ],
                [
                    382,
                    219
                ],
                [
                    430,
                    253
                ],
                [
                    483,
                    184
                ]
            ]
        },
        {
            "label": "farmland",
            "polygon": [
                [
                    512,
                    199
                ],
                [
                    512,
                    161
                ],
                [
                    510,
                    159
                ],
                [
                    493,
                    175
                ],
                [
                    497,
                    181
                ],
                [
                    490,
                    189
                ],
                [
                    484,
                    187
                ],
                [
                    432,
                    255
                ],
                [
                    450,
                    271
                ]
            ]
        },
        {
            "label": "farmland",
            "polygon": [
                [
                    512,
                    147
                ],
                [
                    512,
                    76
                ],
                [
                    509,
                    74
                ],
                [
                    472,
                    117
                ],
                [
                    509,
                    150
                ]
            ]
        }
    ]
}